im_squonk2_client-6.1.0.dist-info/licenses/LICENSE
squonk2/__init__.py
squonk2/api.py
squonk2/as_api.py
squonk2/auth.py
squonk2/dm_api.py
squonk2/environment.py
squonk2/ui_api.py
squonk2/examples/__init__.py
squonk2/examples/data_manager/__init__.py
squonk2/examples/data_manager/job_chain.py
im_squonk2_client-6.1.0.dist-info/METADATA
im_squonk2_client-6.1.0.dist-info/WHEEL
im_squonk2_client-6.1.0.dist-info/top_level.txt
im_squonk2_client-6.1.0.dist-info/RECORD
