Metadata-Version: 2.4
Name: im-squonk2-client
Version: 6.1.0
Summary: Squonk2 Python Client
Home-page: https://github.com/informaticsmatters/squonk2-python-client
Author: Alan Christie
Author-email: achristie@informaticsmatters.com
License: MIT
Keywords: api
Platform: any
Classifier: Development Status :: 5 - Production/Stable
Classifier: Environment :: Other Environment
Classifier: Intended Audience :: Developers
Classifier: License :: OSI Approved :: MIT License
Classifier: Programming Language :: Python :: 3.10
Classifier: Topic :: Software Development :: Libraries :: Python Modules
Classifier: Operating System :: POSIX :: Linux
Requires-Python: >=3
License-File: LICENSE
Requires-Dist: authlib<2.0,>=1.0.1
Requires-Dist: munch<5.0,>=4.0.0
Requires-Dist: pyyaml<7.0,>=5.2
Requires-Dist: requests>=2.22.0
Requires-Dist: wrapt<2.0,>=1.14.1
Dynamic: author
Dynamic: author-email
Dynamic: classifier
Dynamic: description
Dynamic: home-page
Dynamic: keywords
Dynamic: license
Dynamic: license-file
Dynamic: platform
Dynamic: requires-dist
Dynamic: requires-python
Dynamic: summary
